dramatiq_eager_broker/__init__.py
dramatiq_eager_broker/broker.py
dramatiq_eager_broker-0.1.0.dist-info/WHEEL
dramatiq_eager_broker-0.1.0.dist-info/METADATA
dramatiq_eager_broker-0.1.0.dist-info/RECORD
