Metadata-Version: 2.3
Name: dramatiq-eager-broker
Version: 0.1.0
Summary: Eager broker for dramatiq
License: MIT
Requires-Dist: dramatiq>=1.15.0
Requires-Python: >=3.10
Project-URL: repository, https://codeberg.org/yaal/dramatiq-eager-broker
